{
    "swagger": "2.0",
    "info": {
        "contact": {}
    },
    "paths": {
        "/config": {
            "get": {
                "description": "shows config of the project only on the development phase",
                "consumes": [
                    "application/json"
                ],
                "produces": [
                    "application/json"
                ],
                "tags": [
                    "config"
                ],
                "summary": "gets project config",
                "operationId": "get-config",
                "parameters": [
                    {
                        "type": "string",
                        "description": "name",
                        "name": "name",
                        "in": "query",
                        "required": true
                    }
                ],
                "responses": {
                    "200": {
                        "description": "desc",
                        "schema": {
                            "allOf": [
                                {
                                    "$ref": "#/definitions/models.ResponseModel"
                                },
                                {
                                    "type": "object",
                                    "properties": {
                                        "data": {
                                            "$ref": "#/definitions/config.Config"
                                        }
                                    }
                                }
                            ]
                        }
                    },
                    "400": {
                        "description": "Bad Request",
                        "schema": {
                            "allOf": [
                                {
                                    "$ref": "#/definitions/models.ResponseModel"
                                },
                                {
                                    "type": "object",
                                    "properties": {
                                        "error": {
                                            "type": "string"
                                        }
                                    }
                                }
                            ]
                        }
                    },
                    "500": {
                        "description": "Server Error",
                        "schema": {
                            "allOf": [
                                {
                                    "$ref": "#/definitions/models.ResponseModel"
                                },
                                {
                                    "type": "object",
                                    "properties": {
                                        "error": {
                                            "type": "string"
                                        }
                                    }
                                }
                            ]
                        }
                    }
                }
            }
        },
        "/v1/ping": {
            "get": {
                "description": "this returns \"pong\" messsage to show service is working",
                "consumes": [
                    "application/json"
                ],
                "produces": [
                    "application/json"
                ],
                "tags": [
                    "config"
                ],
                "summary": "returns \"pong\" message",
                "operationId": "ping",
                "responses": {
                    "200": {
                        "description": "desc",
                        "schema": {
                            "allOf": [
                                {
                                    "$ref": "#/definitions/models.ResponseModel"
                                },
                                {
                                    "type": "object",
                                    "properties": {
                                        "data": {
                                            "type": "string"
                                        }
                                    }
                                }
                            ]
                        }
                    },
                    "500": {
                        "description": "Internal Server Error",
                        "schema": {
                            "allOf": [
                                {
                                    "$ref": "#/definitions/models.ResponseModel"
                                },
                                {
                                    "type": "object",
                                    "properties": {
                                        "error": {
                                            "type": "string"
                                        }
                                    }
                                }
                            ]
                        }
                    }
                }
            }
        },
        "/v1/profession": {
            "get": {
                "description": "get profession",
                "consumes": [
                    "application/json"
                ],
                "produces": [
                    "application/json"
                ],
                "tags": [
                    "profession"
                ],
                "summary": "get profession",
                "operationId": "get-profession",
                "parameters": [
                    {
                        "type": "string",
                        "description": "search",
                        "name": "search",
                        "in": "query"
                    },
                    {
                        "type": "integer",
                        "description": "limit",
                        "name": "limit",
                        "in": "query"
                    },
                    {
                        "type": "integer",
                        "description": "offset",
                        "name": "offset",
                        "in": "query"
                    }
                ],
                "responses": {
                    "200": {
                        "description": "desc",
                        "schema": {
                            "allOf": [
                                {
                                    "$ref": "#/definitions/models.ResponseModel"
                                },
                                {
                                    "type": "object",
                                    "properties": {
                                        "data": {
                                            "$ref": "#/definitions/position_service.GetAllProfessionResponse"
                                        }
                                    }
                                }
                            ]
                        }
                    },
                    "400": {
                        "description": "Bad Request",
                        "schema": {
                            "allOf": [
                                {
                                    "$ref": "#/definitions/models.ResponseModel"
                                },
                                {
                                    "type": "object",
                                    "properties": {
                                        "error": {
                                            "type": "string"
                                        }
                                    }
                                }
                            ]
                        }
                    },
                    "500": {
                        "description": "Server Error",
                        "schema": {
                            "allOf": [
                                {
                                    "$ref": "#/definitions/models.ResponseModel"
                                },
                                {
                                    "type": "object",
                                    "properties": {
                                        "error": {
                                            "type": "string"
                                        }
                                    }
                                }
                            ]
                        }
                    }
                }
            },
            "post": {
                "description": "create profession",
                "consumes": [
                    "application/json"
                ],
                "produces": [
                    "application/json"
                ],
                "tags": [
                    "profession"
                ],
                "summary": "create profession",
                "operationId": "create-profession",
                "parameters": [
                    {
                        "description": "profession",
                        "name": "profession",
                        "in": "body",
                        "required": true,
                        "schema": {
                            "$ref": "#/definitions/position_service.CreateProfessionRequest"
                        }
                    }
                ],
                "responses": {
                    "200": {
                        "description": "desc",
                        "schema": {
                            "allOf": [
                                {
                                    "$ref": "#/definitions/models.ResponseModel"
                                },
                                {
                                    "type": "object",
                                    "properties": {
                                        "data": {
                                            "$ref": "#/definitions/position_service.Profession"
                                        }
                                    }
                                }
                            ]
                        }
                    },
                    "400": {
                        "description": "Bad Request",
                        "schema": {
                            "allOf": [
                                {
                                    "$ref": "#/definitions/models.ResponseModel"
                                },
                                {
                                    "type": "object",
                                    "properties": {
                                        "error": {
                                            "type": "string"
                                        }
                                    }
                                }
                            ]
                        }
                    },
                    "500": {
                        "description": "Server Error",
                        "schema": {
                            "allOf": [
                                {
                                    "$ref": "#/definitions/models.ResponseModel"
                                },
                                {
                                    "type": "object",
                                    "properties": {
                                        "error": {
                                            "type": "string"
                                        }
                                    }
                                }
                            ]
                        }
                    }
                }
            }
        }
    },
    "definitions": {
        "config.Config": {
            "type": "object",
            "properties": {
                "environment": {
                    "description": "develop, staging, production",
                    "type": "string"
                },
                "httpPort": {
                    "type": "string"
                },
                "logLevel": {
                    "type": "string"
                },
                "positionServiceHost": {
                    "type": "string"
                },
                "positionServicePort": {
                    "type": "integer"
                }
            }
        },
        "models.ResponseModel": {
            "type": "object",
            "properties": {
                "code": {
                    "type": "integer"
                },
                "data": {},
                "error": {},
                "message": {
                    "type": "string"
                }
            }
        },
        "position_service.CreateProfessionRequest": {
            "type": "object",
            "properties": {
                "name": {
                    "type": "string"
                }
            }
        },
        "position_service.GetAllProfessionResponse": {
            "type": "object",
            "properties": {
                "count": {
                    "type": "integer"
                },
                "professions": {
                    "type": "array",
                    "items": {
                        "$ref": "#/definitions/position_service.Profession"
                    }
                }
            }
        },
        "position_service.Profession": {
            "type": "object",
            "properties": {
                "id": {
                    "type": "string"
                },
                "name": {
                    "type": "string"
                }
            }
        }
    },
    "securityDefinitions": {
        "ApiKeyAuth": {
            "type": "apiKey",
            "name": "Authorization",
            "in": "header"
        }
    }
}